pyspyne/__init__.py
pyspyne/broccoli.py
pyspyne/catalyst_setup.py
pyspyne/photon_setup.py
pyspyne/spyne.py
pyspyne-1.2.7.dist-info/LICENSE
pyspyne-1.2.7.dist-info/METADATA
pyspyne-1.2.7.dist-info/WHEEL
pyspyne-1.2.7.dist-info/top_level.txt
pyspyne-1.2.7.dist-info/RECORD
