Metadata-Version: 2.1
Name: pyspyne
Version: 1.2.7
Summary: The All-in-One Python Package
Home-page: UNKNOWN
Author: Arjun Palakkal
Author-email: arjunpalakkal@gmail.com
License: UNKNOWN
Platform: UNKNOWN
Classifier: Programming Language :: Python :: 3
Classifier: License :: OSI Approved :: MIT License
Classifier: Operating System :: OS Independent
Requires-Python: >=3.7
License-File: LICENSE
